[
    {
        "_rid": 5750,
        "Id": "Metadata/Items/Rings/RingDemigods1",
        "ItemClassesKey": 5,
        "Width": 1,
        "Height": 1,
        "Name": "Golden Hoop",
        "InheritsFrom": "Metadata/Items/Rings/AbstractRing",
        "DropLevel": 12,
        "FlavourTextKey": null,
        "Implicit_ModsKeys": [
            279
        ],
        "SizeOnGround": 1,
        "SoundEffect": null,
        "TagsKeys": [
            33,
            709
        ],
        "ModDomain": 1,
        "SiteVisibility": 1,
        "ItemVisualIdentity": 7367,
        "HASH32": -1015727274,
        "VendorRecipe_AchievementItems": [],
        "Inflection": "",
        "Equip_AchievementItemsKey": null,
        "IsCorrupted": false,
        "Identify_AchievementItems": [],
        "IdentifyMagic_AchievementItems": [],
        "FragmentBaseItemTypesKey": null,
        "Unknown24": false,
        "Unknown25": null,
        "Unknown26": null,
        "Unknown27": false,
        "TradeMarketCategory": null,
        "Unmodifiable": false,
        "Achievement": [],
        "Unknown31": [],
        "IgnoreQuantBonus": false,
        "Unknown33": false
    },
    {
        "_rid": 5751,
        "Id": "Metadata/Items/Rings/Ring1",
        "ItemClassesKey": 5,
        "Width": 1,
        "Height": 1,
        "Name": "Iron Ring",
        "InheritsFrom": "Metadata/Items/Rings/AbstractRing",
        "DropLevel": 2,
        "FlavourTextKey": null,
        "Implicit_ModsKeys": [
            797
        ],
        "SizeOnGround": 1,
        "SoundEffect": null,
        "TagsKeys": [],
        "ModDomain": 1,
        "SiteVisibility": 1,
        "ItemVisualIdentity": 7339,
        "HASH32": -2140695749,
        "VendorRecipe_AchievementItems": [],
        "Inflection": "",
        "Equip_AchievementItemsKey": null,
        "IsCorrupted": false,
        "Identify_AchievementItems": [],
        "IdentifyMagic_AchievementItems": [],
        "FragmentBaseItemTypesKey": null,
        "Unknown24": false,
        "Unknown25": null,
        "Unknown26": null,
        "Unknown27": false,
        "TradeMarketCategory": null,
        "Unmodifiable": false,
        "Achievement": [],
        "Unknown31": [],
        "IgnoreQuantBonus": false,
        "Unknown33": false
    },
    {
        "_rid": 5752,
        "Id": "Metadata/Items/Rings/Ring2",
        "ItemClassesKey": 5,
        "Width": 1,
        "Height": 1,
        "Name": "Coral Ring",
        "InheritsFrom": "Metadata/Items/Rings/AbstractRing",
        "DropLevel": 4,
        "FlavourTextKey": null,
        "Implicit_ModsKeys": [
            344
        ],
        "SizeOnGround": 1,
        "SoundEffect": null,
        "TagsKeys": [],
        "ModDomain": 1,
        "SiteVisibility": 1,
        "ItemVisualIdentity": 7340,
        "HASH32": -1209177664,
        "VendorRecipe_AchievementItems": [],
        "Inflection": "",
        "Equip_AchievementItemsKey": 7695,
        "IsCorrupted": false,
        "Identify_AchievementItems": [],
        "IdentifyMagic_AchievementItems": [],
        "FragmentBaseItemTypesKey": null,
        "Unknown24": false,
        "Unknown25": null,
        "Unknown26": null,
        "Unknown27": false,
        "TradeMarketCategory": null,
        "Unmodifiable": false,
        "Achievement": [],
        "Unknown31": [],
        "IgnoreQuantBonus": false,
        "Unknown33": false
    },
    {
        "_rid": 5753,
        "Id": "Metadata/Items/Rings/Ring3",
        "ItemClassesKey": 5,
        "Width": 1,
        "Height": 1,
        "Name": "Paua Ring",
        "InheritsFrom": "Metadata/Items/Rings/AbstractRing",
        "DropLevel": 5,
        "FlavourTextKey": null,
        "Implicit_ModsKeys": [
            563
        ],
        "SizeOnGround": 1,
        "SoundEffect": null,
        "TagsKeys": [],
        "ModDomain": 1,
        "SiteVisibility": 1,
        "ItemVisualIdentity": 7341,
        "HASH32": 1479167233,
        "VendorRecipe_AchievementItems": [],
        "Inflection": "",
        "Equip_AchievementItemsKey": null,
        "IsCorrupted": false,
        "Identify_AchievementItems": [],
        "IdentifyMagic_AchievementItems": [],
        "FragmentBaseItemTypesKey": null,
        "Unknown24": false,
        "Unknown25": null,
        "Unknown26": null,
        "Unknown27": false,
        "TradeMarketCategory": null,
        "Unmodifiable": false,
        "Achievement": [],
        "Unknown31": [],
        "IgnoreQuantBonus": false,
        "Unknown33": false
    },
    {
        "_rid": 5754,
        "Id": "Metadata/Items/Rings/Ring4",
        "ItemClassesKey": 5,
        "Width": 1,
        "Height": 1,
        "Name": "Gold Ring",
        "InheritsFrom": "Metadata/Items/Rings/AbstractRing",
        "DropLevel": 20,
        "FlavourTextKey": null,
        "Implicit_ModsKeys": [
            2599
        ],
        "SizeOnGround": 1,
        "SoundEffect": null,
        "TagsKeys": [],
        "ModDomain": 1,
        "SiteVisibility": 1,
        "ItemVisualIdentity": 7342,
        "HASH32": 704083608,
        "VendorRecipe_AchievementItems": [],
        "Inflection": "",
        "Equip_AchievementItemsKey": null,
        "IsCorrupted": false,
        "Identify_AchievementItems": [],
        "IdentifyMagic_AchievementItems": [],
        "FragmentBaseItemTypesKey": null,
        "Unknown24": false,
        "Unknown25": null,
        "Unknown26": null,
        "Unknown27": false,
        "TradeMarketCategory": null,
        "Unmodifiable": false,
        "Achievement": [],
        "Unknown31": [],
        "IgnoreQuantBonus": false,
        "Unknown33": false
    },
    {
        "_rid": 5755,
        "Id": "Metadata/Items/Rings/Ring5",
        "ItemClassesKey": 5,
        "Width": 1,
        "Height": 1,
        "Name": "Topaz Ring",
        "InheritsFrom": "Metadata/Items/Rings/AbstractRing",
        "DropLevel": 12,
        "FlavourTextKey": null,
        "Implicit_ModsKeys": [
            3311
        ],
        "SizeOnGround": 1,
        "SoundEffect": null,
        "TagsKeys": [],
        "ModDomain": 1,
        "SiteVisibility": 1,
        "ItemVisualIdentity": 7343,
        "HASH32": 1541498802,
        "VendorRecipe_AchievementItems": [
            10366
        ],
        "Inflection": "",
        "Equip_AchievementItemsKey": 8242,
        "IsCorrupted": false,
        "Identify_AchievementItems": [],
        "IdentifyMagic_AchievementItems": [],
        "FragmentBaseItemTypesKey": null,
        "Unknown24": false,
        "Unknown25": null,
        "Unknown26": null,
        "Unknown27": false,
        "TradeMarketCategory": null,
        "Unmodifiable": false,
        "Achievement": [],
        "Unknown31": [],
        "IgnoreQuantBonus": false,
        "Unknown33": false
    },
    {
        "_rid": 5756,
        "Id": "Metadata/Items/Rings/Ring6",
        "ItemClassesKey": 5,
        "Width": 1,
        "Height": 1,
        "Name": "Sapphire Ring",
        "InheritsFrom": "Metadata/Items/Rings/AbstractRing",
        "DropLevel": 8,
        "FlavourTextKey": null,
        "Implicit_ModsKeys": [
            3224
        ],
        "SizeOnGround": 1,
        "SoundEffect": null,
        "TagsKeys": [],
        "ModDomain": 1,
        "SiteVisibility": 1,
        "ItemVisualIdentity": 7344,
        "HASH32": -1133644982,
        "VendorRecipe_AchievementItems": [
            10366
        ],
        "Inflection": "",
        "Equip_AchievementItemsKey": 8242,
        "IsCorrupted": false,
        "Identify_AchievementItems": [],
        "IdentifyMagic_AchievementItems": [],
        "FragmentBaseItemTypesKey": null,
        "Unknown24": false,
        "Unknown25": null,
        "Unknown26": null,
        "Unknown27": false,
        "TradeMarketCategory": null,
        "Unmodifiable": false,
        "Achievement": [],
        "Unknown31": [],
        "IgnoreQuantBonus": false,
        "Unknown33": false
    },
    {
        "_rid": 5757,
        "Id": "Metadata/Items/Rings/Ring7",
        "ItemClassesKey": 5,
        "Width": 1,
        "Height": 1,
        "Name": "Ruby Ring",
        "InheritsFrom": "Metadata/Items/Rings/AbstractRing",
        "DropLevel": 16,
        "FlavourTextKey": null,
        "Implicit_ModsKeys": [
            3151
        ],
        "SizeOnGround": 1,
        "SoundEffect": null,
        "TagsKeys": [],
        "ModDomain": 1,
        "SiteVisibility": 1,
        "ItemVisualIdentity": 7345,
        "HASH32": 2058013038,
        "VendorRecipe_AchievementItems": [
            10366
        ],
        "Inflection": "",
        "Equip_AchievementItemsKey": 8242,
        "IsCorrupted": false,
        "Identify_AchievementItems": [],
        "IdentifyMagic_AchievementItems": [],
        "FragmentBaseItemTypesKey": null,
        "Unknown24": false,
        "Unknown25": null,
        "Unknown26": null,
        "Unknown27": false,
        "TradeMarketCategory": null,
        "Unmodifiable": false,
        "Achievement": [],
        "Unknown31": [],
        "IgnoreQuantBonus": false,
        "Unknown33": false
    },
    {
        "_rid": 5758,
        "Id": "Metadata/Items/Rings/Ring8",
        "ItemClassesKey": 5,
        "Width": 1,
        "Height": 1,
        "Name": "Prismatic Ring",
        "InheritsFrom": "Metadata/Items/Rings/AbstractRing",
        "DropLevel": 30,
        "FlavourTextKey": null,
        "Implicit_ModsKeys": [
            3454
        ],
        "SizeOnGround": 1,
        "SoundEffect": null,
        "TagsKeys": [],
        "ModDomain": 1,
        "SiteVisibility": 1,
        "ItemVisualIdentity": 7346,
        "HASH32": -1943485937,
        "VendorRecipe_AchievementItems": [
            10445
        ],
        "Inflection": "",
        "Equip_AchievementItemsKey": null,
        "IsCorrupted": false,
        "Identify_AchievementItems": [],
        "IdentifyMagic_AchievementItems": [],
        "FragmentBaseItemTypesKey": null,
        "Unknown24": false,
        "Unknown25": null,
        "Unknown26": null,
        "Unknown27": false,
        "TradeMarketCategory": null,
        "Unmodifiable": false,
        "Achievement": [],
        "Unknown31": [],
        "IgnoreQuantBonus": false,
        "Unknown33": false
    },
    {
        "_rid": 5759,
        "Id": "Metadata/Items/Rings/Ring9",
        "ItemClassesKey": 5,
        "Width": 1,
        "Height": 1,
        "Name": "Moonstone Ring",
        "InheritsFrom": "Metadata/Items/Rings/AbstractRing",
        "DropLevel": 25,
        "FlavourTextKey": null,
        "Implicit_ModsKeys": [
            681
        ],
        "SizeOnGround": 1,
        "SoundEffect": null,
        "TagsKeys": [],
        "ModDomain": 1,
        "SiteVisibility": 1,
        "ItemVisualIdentity": 7347,
        "HASH32": 1517309305,
        "VendorRecipe_AchievementItems": [],
        "Inflection": "",
        "Equip_AchievementItemsKey": null,
        "IsCorrupted": false,
        "Identify_AchievementItems": [],
        "IdentifyMagic_AchievementItems": [],
        "FragmentBaseItemTypesKey": null,
        "Unknown24": false,
        "Unknown25": null,
        "Unknown26": null,
        "Unknown27": false,
        "TradeMarketCategory": null,
        "Unmodifiable": false,
        "Achievement": [],
        "Unknown31": [],
        "IgnoreQuantBonus": false,
        "Unknown33": false
    },
    {
        "_rid": 5760,
        "Id": "Metadata/Items/Rings/Ring10",
        "ItemClassesKey": 5,
        "Width": 1,
        "Height": 1,
        "Name": "Amethyst Ring",
        "InheritsFrom": "Metadata/Items/Rings/AbstractRing",
        "DropLevel": 38,
        "FlavourTextKey": null,
        "Implicit_ModsKeys": [
            3384
        ],
        "SizeOnGround": 1,
        "SoundEffect": null,
        "TagsKeys": [],
        "ModDomain": 1,
        "SiteVisibility": 1,
        "ItemVisualIdentity": 7348,
        "HASH32": -1645590109,
        "VendorRecipe_AchievementItems": [],
        "Inflection": "",
        "Equip_AchievementItemsKey": null,
        "IsCorrupted": false,
        "Identify_AchievementItems": [],
        "IdentifyMagic_AchievementItems": [],
        "FragmentBaseItemTypesKey": null,
        "Unknown24": false,
        "Unknown25": null,
        "Unknown26": null,
        "Unknown27": false,
        "TradeMarketCategory": null,
        "Unmodifiable": false,
        "Achievement": [],
        "Unknown31": [],
        "IgnoreQuantBonus": false,
        "Unknown33": false
    },
    {
        "_rid": 5761,
        "Id": "Metadata/Items/Rings/Ring11",
        "ItemClassesKey": 5,
        "Width": 1,
        "Height": 1,
        "Name": "Diamond Ring",
        "InheritsFrom": "Metadata/Items/Rings/AbstractRing",
        "DropLevel": 25,
        "FlavourTextKey": null,
        "Implicit_ModsKeys": [
            3092
        ],
        "SizeOnGround": 1,
        "SoundEffect": null,
        "TagsKeys": [],
        "ModDomain": 1,
        "SiteVisibility": 1,
        "ItemVisualIdentity": 7349,
        "HASH32": -1189043586,
        "VendorRecipe_AchievementItems": [],
        "Inflection": "",
        "Equip_AchievementItemsKey": null,
        "IsCorrupted": false,
        "Identify_AchievementItems": [],
        "IdentifyMagic_AchievementItems": [],
        "FragmentBaseItemTypesKey": null,
        "Unknown24": false,
        "Unknown25": null,
        "Unknown26": null,
        "Unknown27": false,
        "TradeMarketCategory": null,
        "Unmodifiable": false,
        "Achievement": [],
        "Unknown31": [],
        "IgnoreQuantBonus": false,
        "Unknown33": false
    },
    {
        "_rid": 5762,
        "Id": "Metadata/Items/Rings/Ring12",
        "ItemClassesKey": 5,
        "Width": 1,
        "Height": 1,
        "Name": "Two-Stone Ring",
        "InheritsFrom": "Metadata/Items/Rings/AbstractRing",
        "DropLevel": 20,
        "FlavourTextKey": null,
        "Implicit_ModsKeys": [
            3430
        ],
        "SizeOnGround": 1,
        "SoundEffect": null,
        "TagsKeys": [
            148
        ],
        "ModDomain": 1,
        "SiteVisibility": 1,
        "ItemVisualIdentity": 7350,
        "HASH32": -972952859,
        "VendorRecipe_AchievementItems": [],
        "Inflection": "",
        "Equip_AchievementItemsKey": null,
        "IsCorrupted": false,
        "Identify_AchievementItems": [],
        "IdentifyMagic_AchievementItems": [],
        "FragmentBaseItemTypesKey": null,
        "Unknown24": false,
        "Unknown25": null,
        "Unknown26": null,
        "Unknown27": false,
        "TradeMarketCategory": null,
        "Unmodifiable": false,
        "Achievement": [],
        "Unknown31": [],
        "IgnoreQuantBonus": false,
        "Unknown33": false
    },
    {
        "_rid": 5763,
        "Id": "Metadata/Items/Rings/Ring13",
        "ItemClassesKey": 5,
        "Width": 1,
        "Height": 1,
        "Name": "Two-Stone Ring",
        "InheritsFrom": "Metadata/Items/Rings/AbstractRing",
        "DropLevel": 20,
        "FlavourTextKey": null,
        "Implicit_ModsKeys": [
            3431
        ],
        "SizeOnGround": 1,
        "SoundEffect": null,
        "TagsKeys": [
            148
        ],
        "ModDomain": 1,
        "SiteVisibility": 0,
        "ItemVisualIdentity": 7351,
        "HASH32": 769564432,
        "VendorRecipe_AchievementItems": [],
        "Inflection": "",
        "Equip_AchievementItemsKey": null,
        "IsCorrupted": false,
        "Identify_AchievementItems": [],
        "IdentifyMagic_AchievementItems": [],
        "FragmentBaseItemTypesKey": null,
        "Unknown24": false,
        "Unknown25": null,
        "Unknown26": null,
        "Unknown27": false,
        "TradeMarketCategory": null,
        "Unmodifiable": false,
        "Achievement": [],
        "Unknown31": [],
        "IgnoreQuantBonus": false,
        "Unknown33": false
    },
    {
        "_rid": 5764,
        "Id": "Metadata/Items/Rings/Ring14",
        "ItemClassesKey": 5,
        "Width": 1,
        "Height": 1,
        "Name": "Two-Stone Ring",
        "InheritsFrom": "Metadata/Items/Rings/AbstractRing",
        "DropLevel": 20,
        "FlavourTextKey": null,
        "Implicit_ModsKeys": [
            3432
        ],
        "SizeOnGround": 1,
        "SoundEffect": null,
        "TagsKeys": [
            148
        ],
        "ModDomain": 1,
        "SiteVisibility": 0,
        "ItemVisualIdentity": 7352,
        "HASH32": 1778311337,
        "VendorRecipe_AchievementItems": [],
        "Inflection": "",
        "Equip_AchievementItemsKey": null,
        "IsCorrupted": false,
        "Identify_AchievementItems": [],
        "IdentifyMagic_AchievementItems": [],
        "FragmentBaseItemTypesKey": null,
        "Unknown24": false,
        "Unknown25": null,
        "Unknown26": null,
        "Unknown27": false,
        "TradeMarketCategory": null,
        "Unmodifiable": false,
        "Achievement": [],
        "Unknown31": [],
        "IgnoreQuantBonus": false,
        "Unknown33": false
    },
    {
        "_rid": 5765,
        "Id": "Metadata/Items/Rings/Ring15",
        "ItemClassesKey": 5,
        "Width": 1,
        "Height": 1,
        "Name": "Unset Ring",
        "InheritsFrom": "Metadata/Items/Rings/AbstractRing",
        "DropLevel": 45,
        "FlavourTextKey": null,
        "Implicit_ModsKeys": [
            7842
        ],
        "SizeOnGround": 1,
        "SoundEffect": null,
        "TagsKeys": [
            220
        ],
        "ModDomain": 1,
        "SiteVisibility": 1,
        "ItemVisualIdentity": 7353,
        "HASH32": 303449393,
        "VendorRecipe_AchievementItems": [],
        "Inflection": "",
        "Equip_AchievementItemsKey": null,
        "IsCorrupted": false,
        "Identify_AchievementItems": [],
        "IdentifyMagic_AchievementItems": [],
        "FragmentBaseItemTypesKey": null,
        "Unknown24": false,
        "Unknown25": null,
        "Unknown26": null,
        "Unknown27": false,
        "TradeMarketCategory": null,
        "Unmodifiable": false,
        "Achievement": [],
        "Unknown31": [],
        "IgnoreQuantBonus": false,
        "Unknown33": false
    },
    {
        "_rid": 5766,
        "Id": "Metadata/Items/Rings/Ring16",
        "ItemClassesKey": 5,
        "Width": 1,
        "Height": 1,
        "Name": "Bone Ring",
        "InheritsFrom": "Metadata/Items/Rings/AbstractRing",
        "DropLevel": 30,
        "FlavourTextKey": null,
        "Implicit_ModsKeys": [
            20740
        ],
        "SizeOnGround": 1,
        "SoundEffect": null,
        "TagsKeys": [
            1005
        ],
        "ModDomain": 1,
        "SiteVisibility": 1,
        "ItemVisualIdentity": 7354,
        "HASH32": 946296587,
        "VendorRecipe_AchievementItems": [],
        "Inflection": "",
        "Equip_AchievementItemsKey": null,
        "IsCorrupted": false,
        "Identify_AchievementItems": [],
        "IdentifyMagic_AchievementItems": [],
        "FragmentBaseItemTypesKey": null,
        "Unknown24": false,
        "Unknown25": null,
        "Unknown26": null,
        "Unknown27": false,
        "TradeMarketCategory": null,
        "Unmodifiable": false,
        "Achievement": [],
        "Unknown31": [],
        "IgnoreQuantBonus": false,
        "Unknown33": false
    },
    {
        "_rid": 5767,
        "Id": "Metadata/Items/Rings/RingE1",
        "ItemClassesKey": 5,
        "Width": 1,
        "Height": 1,
        "Name": "Cogwork Ring",
        "InheritsFrom": "Metadata/Items/Rings/AbstractRing",
        "DropLevel": 68,
        "FlavourTextKey": null,
        "Implicit_ModsKeys": [
            24157
        ],
        "SizeOnGround": 1,
        "SoundEffect": null,
        "TagsKeys": [
            33,
            1061
        ],
        "ModDomain": 1,
        "SiteVisibility": 1,
        "ItemVisualIdentity": 7355,
        "HASH32": -971906502,
        "VendorRecipe_AchievementItems": [],
        "Inflection": "",
        "Equip_AchievementItemsKey": 7322,
        "IsCorrupted": false,
        "Identify_AchievementItems": [],
        "IdentifyMagic_AchievementItems": [],
        "FragmentBaseItemTypesKey": null,
        "Unknown24": false,
        "Unknown25": null,
        "Unknown26": null,
        "Unknown27": false,
        "TradeMarketCategory": null,
        "Unmodifiable": false,
        "Achievement": [
            10449
        ],
        "Unknown31": [],
        "IgnoreQuantBonus": false,
        "Unknown33": false
    },
    {
        "_rid": 5768,
        "Id": "Metadata/Items/Rings/RingE2",
        "ItemClassesKey": 5,
        "Width": 1,
        "Height": 1,
        "Name": "Geodesic Ring",
        "InheritsFrom": "Metadata/Items/Rings/AbstractRing",
        "DropLevel": 68,
        "FlavourTextKey": null,
        "Implicit_ModsKeys": [
            24158
        ],
        "SizeOnGround": 1,
        "SoundEffect": null,
        "TagsKeys": [
            33,
            1061
        ],
        "ModDomain": 1,
        "SiteVisibility": 1,
        "ItemVisualIdentity": 7356,
        "HASH32": -1691395426,
        "VendorRecipe_AchievementItems": [],
        "Inflection": "",
        "Equip_AchievementItemsKey": 7322,
        "IsCorrupted": false,
        "Identify_AchievementItems": [],
        "IdentifyMagic_AchievementItems": [],
        "FragmentBaseItemTypesKey": null,
        "Unknown24": false,
        "Unknown25": null,
        "Unknown26": null,
        "Unknown27": false,
        "TradeMarketCategory": null,
        "Unmodifiable": false,
        "Achievement": [
            10449
        ],
        "Unknown31": [],
        "IgnoreQuantBonus": false,
        "Unknown33": false
    },
    {
        "_rid": 5769,
        "Id": "Metadata/Items/Rings/RingE3",
        "ItemClassesKey": 5,
        "Width": 1,
        "Height": 1,
        "Name": "Composite Ring",
        "InheritsFrom": "Metadata/Items/Rings/AbstractRing",
        "DropLevel": 68,
        "FlavourTextKey": null,
        "Implicit_ModsKeys": [
            24159
        ],
        "SizeOnGround": 1,
        "SoundEffect": null,
        "TagsKeys": [
            33,
            1061
        ],
        "ModDomain": 1,
        "SiteVisibility": 1,
        "ItemVisualIdentity": 7357,
        "HASH32": 213822455,
        "VendorRecipe_AchievementItems": [],
        "Inflection": "",
        "Equip_AchievementItemsKey": 7322,
        "IsCorrupted": false,
        "Identify_AchievementItems": [],
        "IdentifyMagic_AchievementItems": [],
        "FragmentBaseItemTypesKey": null,
        "Unknown24": false,
        "Unknown25": null,
        "Unknown26": null,
        "Unknown27": false,
        "TradeMarketCategory": null,
        "Unmodifiable": false,
        "Achievement": [
            10449
        ],
        "Unknown31": [],
        "IgnoreQuantBonus": false,
        "Unknown33": false
    },
    {
        "_rid": 5770,
        "Id": "Metadata/Items/Rings/RingE4",
        "ItemClassesKey": 5,
        "Width": 1,
        "Height": 1,
        "Name": "Manifold Ring",
        "InheritsFrom": "Metadata/Items/Rings/AbstractRing",
        "DropLevel": 75,
        "FlavourTextKey": null,
        "Implicit_ModsKeys": [
            24160
        ],
        "SizeOnGround": 1,
        "SoundEffect": null,
        "TagsKeys": [
            33,
            1061
        ],
        "ModDomain": 1,
        "SiteVisibility": 1,
        "ItemVisualIdentity": 7358,
        "HASH32": 1461354247,
        "VendorRecipe_AchievementItems": [],
        "Inflection": "",
        "Equip_AchievementItemsKey": 7322,
        "IsCorrupted": false,
        "Identify_AchievementItems": [],
        "IdentifyMagic_AchievementItems": [],
        "FragmentBaseItemTypesKey": null,
        "Unknown24": false,
        "Unknown25": null,
        "Unknown26": null,
        "Unknown27": false,
        "TradeMarketCategory": null,
        "Unmodifiable": false,
        "Achievement": [
            10449
        ],
        "Unknown31": [],
        "IgnoreQuantBonus": false,
        "Unknown33": false
    },
    {
        "_rid": 5771,
        "Id": "Metadata/Items/Rings/RingE5",
        "ItemClassesKey": 5,
        "Width": 1,
        "Height": 1,
        "Name": "Ratcheting Ring",
        "InheritsFrom": "Metadata/Items/Rings/AbstractRing",
        "DropLevel": 68,
        "FlavourTextKey": null,
        "Implicit_ModsKeys": [
            24161
        ],
        "SizeOnGround": 1,
        "SoundEffect": null,
        "TagsKeys": [
            33,
            1061
        ],
        "ModDomain": 1,
        "SiteVisibility": 1,
        "ItemVisualIdentity": 7359,
        "HASH32": -1868646459,
        "VendorRecipe_AchievementItems": [],
        "Inflection": "",
        "Equip_AchievementItemsKey": 7322,
        "IsCorrupted": false,
        "Identify_AchievementItems": [],
        "IdentifyMagic_AchievementItems": [],
        "FragmentBaseItemTypesKey": null,
        "Unknown24": false,
        "Unknown25": null,
        "Unknown26": null,
        "Unknown27": false,
        "TradeMarketCategory": null,
        "Unmodifiable": false,
        "Achievement": [
            10449
        ],
        "Unknown31": [],
        "IgnoreQuantBonus": false,
        "Unknown33": false
    },
    {
        "_rid": 5772,
        "Id": "Metadata/Items/Rings/RingE6",
        "ItemClassesKey": 5,
        "Width": 1,
        "Height": 1,
        "Name": "Helical Ring",
        "InheritsFrom": "Metadata/Items/Rings/AbstractRing",
        "DropLevel": 75,
        "FlavourTextKey": null,
        "Implicit_ModsKeys": [
            24162
        ],
        "SizeOnGround": 1,
        "SoundEffect": null,
        "TagsKeys": [
            33,
            1061
        ],
        "ModDomain": 1,
        "SiteVisibility": 1,
        "ItemVisualIdentity": 7360,
        "HASH32": 390544172,
        "VendorRecipe_AchievementItems": [],
        "Inflection": "",
        "Equip_AchievementItemsKey": 7322,
        "IsCorrupted": false,
        "Identify_AchievementItems": [],
        "IdentifyMagic_AchievementItems": [],
        "FragmentBaseItemTypesKey": null,
        "Unknown24": false,
        "Unknown25": null,
        "Unknown26": null,
        "Unknown27": false,
        "TradeMarketCategory": null,
        "Unmodifiable": false,
        "Achievement": [
            10449
        ],
        "Unknown31": [],
        "IgnoreQuantBonus": false,
        "Unknown33": false
    },
    {
        "_rid": 5773,
        "Id": "Metadata/Items/Rings/RingK1",
        "ItemClassesKey": 5,
        "Width": 1,
        "Height": 1,
        "Name": "Dusk Ring",
        "InheritsFrom": "Metadata/Items/Rings/AbstractRing",
        "DropLevel": 25,
        "FlavourTextKey": null,
        "Implicit_ModsKeys": [
            24163
        ],
        "SizeOnGround": 1,
        "SoundEffect": null,
        "TagsKeys": [
            33
        ],
        "ModDomain": 1,
        "SiteVisibility": 2,
        "ItemVisualIdentity": 7361,
        "HASH32": 700529725,
        "VendorRecipe_AchievementItems": [],
        "Inflection": "",
        "Equip_AchievementItemsKey": null,
        "IsCorrupted": false,
        "Identify_AchievementItems": [],
        "IdentifyMagic_AchievementItems": [],
        "FragmentBaseItemTypesKey": null,
        "Unknown24": false,
        "Unknown25": null,
        "Unknown26": null,
        "Unknown27": false,
        "TradeMarketCategory": null,
        "Unmodifiable": false,
        "Achievement": [],
        "Unknown31": [],
        "IgnoreQuantBonus": false,
        "Unknown33": false
    },
    {
        "_rid": 5774,
        "Id": "Metadata/Items/Rings/RingK2",
        "ItemClassesKey": 5,
        "Width": 1,
        "Height": 1,
        "Name": "Penumbra Ring",
        "InheritsFrom": "Metadata/Items/Rings/AbstractRing",
        "DropLevel": 25,
        "FlavourTextKey": null,
        "Implicit_ModsKeys": [
            24167
        ],
        "SizeOnGround": 1,
        "SoundEffect": null,
        "TagsKeys": [
            33
        ],
        "ModDomain": 1,
        "SiteVisibility": 2,
        "ItemVisualIdentity": 7362,
        "HASH32": 507164178,
        "VendorRecipe_AchievementItems": [],
        "Inflection": "",
        "Equip_AchievementItemsKey": null,
        "IsCorrupted": false,
        "Identify_AchievementItems": [],
        "IdentifyMagic_AchievementItems": [],
        "FragmentBaseItemTypesKey": null,
        "Unknown24": false,
        "Unknown25": null,
        "Unknown26": null,
        "Unknown27": false,
        "TradeMarketCategory": null,
        "Unmodifiable": false,
        "Achievement": [],
        "Unknown31": [],
        "IgnoreQuantBonus": false,
        "Unknown33": false
    },
    {
        "_rid": 5775,
        "Id": "Metadata/Items/Rings/RingK3",
        "ItemClassesKey": 5,
        "Width": 1,
        "Height": 1,
        "Name": "Gloam Ring",
        "InheritsFrom": "Metadata/Items/Rings/AbstractRing",
        "DropLevel": 25,
        "FlavourTextKey": null,
        "Implicit_ModsKeys": [
            24168
        ],
        "SizeOnGround": 1,
        "SoundEffect": null,
        "TagsKeys": [
            33,
            1005
        ],
        "ModDomain": 1,
        "SiteVisibility": 2,
        "ItemVisualIdentity": 7363,
        "HASH32": -1333432025,
        "VendorRecipe_AchievementItems": [],
        "Inflection": "",
        "Equip_AchievementItemsKey": null,
        "IsCorrupted": false,
        "Identify_AchievementItems": [],
        "IdentifyMagic_AchievementItems": [],
        "FragmentBaseItemTypesKey": null,
        "Unknown24": false,
        "Unknown25": null,
        "Unknown26": null,
        "Unknown27": false,
        "TradeMarketCategory": null,
        "Unmodifiable": false,
        "Achievement": [],
        "Unknown31": [],
        "IgnoreQuantBonus": false,
        "Unknown33": false
    },
    {
        "_rid": 5776,
        "Id": "Metadata/Items/Rings/RingK4",
        "ItemClassesKey": 5,
        "Width": 1,
        "Height": 1,
        "Name": "Tenebrous Ring",
        "InheritsFrom": "Metadata/Items/Rings/AbstractRing",
        "DropLevel": 25,
        "FlavourTextKey": null,
        "Implicit_ModsKeys": [
            24169
        ],
        "SizeOnGround": 1,
        "SoundEffect": null,
        "TagsKeys": [
            33
        ],
        "ModDomain": 1,
        "SiteVisibility": 2,
        "ItemVisualIdentity": 7364,
        "HASH32": 1411087072,
        "VendorRecipe_AchievementItems": [],
        "Inflection": "",
        "Equip_AchievementItemsKey": null,
        "IsCorrupted": false,
        "Identify_AchievementItems": [],
        "IdentifyMagic_AchievementItems": [],
        "FragmentBaseItemTypesKey": null,
        "Unknown24": false,
        "Unknown25": null,
        "Unknown26": null,
        "Unknown27": false,
        "TradeMarketCategory": null,
        "Unmodifiable": false,
        "Achievement": [],
        "Unknown31": [],
        "IgnoreQuantBonus": false,
        "Unknown33": false
    },
    {
        "_rid": 5777,
        "Id": "Metadata/Items/Rings/RingK5a",
        "ItemClassesKey": 5,
        "Width": 1,
        "Height": 1,
        "Name": "Shadowed Ring",
        "InheritsFrom": "Metadata/Items/Rings/AbstractRing",
        "DropLevel": 25,
        "FlavourTextKey": null,
        "Implicit_ModsKeys": [
            24164
        ],
        "SizeOnGround": 1,
        "SoundEffect": null,
        "TagsKeys": [
            33
        ],
        "ModDomain": 1,
        "SiteVisibility": 2,
        "ItemVisualIdentity": 7365,
        "HASH32": -488169718,
        "VendorRecipe_AchievementItems": [],
        "Inflection": "",
        "Equip_AchievementItemsKey": null,
        "IsCorrupted": false,
        "Identify_AchievementItems": [],
        "IdentifyMagic_AchievementItems": [],
        "FragmentBaseItemTypesKey": null,
        "Unknown24": false,
        "Unknown25": null,
        "Unknown26": null,
        "Unknown27": false,
        "TradeMarketCategory": null,
        "Unmodifiable": false,
        "Achievement": [],
        "Unknown31": [],
        "IgnoreQuantBonus": false,
        "Unknown33": false
    },
    {
        "_rid": 5778,
        "Id": "Metadata/Items/Rings/RingK5b",
        "ItemClassesKey": 5,
        "Width": 1,
        "Height": 1,
        "Name": "Shadowed Ring",
        "InheritsFrom": "Metadata/Items/Rings/AbstractRing",
        "DropLevel": 25,
        "FlavourTextKey": null,
        "Implicit_ModsKeys": [
            24165
        ],
        "SizeOnGround": 1,
        "SoundEffect": null,
        "TagsKeys": [
            33
        ],
        "ModDomain": 1,
        "SiteVisibility": 2,
        "ItemVisualIdentity": 7365,
        "HASH32": 1514410094,
        "VendorRecipe_AchievementItems": [],
        "Inflection": "",
        "Equip_AchievementItemsKey": null,
        "IsCorrupted": false,
        "Identify_AchievementItems": [],
        "IdentifyMagic_AchievementItems": [],
        "FragmentBaseItemTypesKey": null,
        "Unknown24": false,
        "Unknown25": null,
        "Unknown26": null,
        "Unknown27": false,
        "TradeMarketCategory": null,
        "Unmodifiable": false,
        "Achievement": [],
        "Unknown31": [],
        "IgnoreQuantBonus": false,
        "Unknown33": false
    },
    {
        "_rid": 5779,
        "Id": "Metadata/Items/Rings/RingK5c",
        "ItemClassesKey": 5,
        "Width": 1,
        "Height": 1,
        "Name": "Shadowed Ring",
        "InheritsFrom": "Metadata/Items/Rings/AbstractRing",
        "DropLevel": 25,
        "FlavourTextKey": null,
        "Implicit_ModsKeys": [
            24166
        ],
        "SizeOnGround": 1,
        "SoundEffect": null,
        "TagsKeys": [
            33
        ],
        "ModDomain": 1,
        "SiteVisibility": 2,
        "ItemVisualIdentity": 7365,
        "HASH32": 132049695,
        "VendorRecipe_AchievementItems": [],
        "Inflection": "",
        "Equip_AchievementItemsKey": null,
        "IsCorrupted": false,
        "Identify_AchievementItems": [],
        "IdentifyMagic_AchievementItems": [],
        "FragmentBaseItemTypesKey": null,
        "Unknown24": false,
        "Unknown25": null,
        "Unknown26": null,
        "Unknown27": false,
        "TradeMarketCategory": null,
        "Unmodifiable": false,
        "Achievement": [],
        "Unknown31": [],
        "IgnoreQuantBonus": false,
        "Unknown33": false
    },
    {
        "_rid": 5780,
        "Id": "Metadata/Items/Rings/RingR1",
        "ItemClassesKey": 5,
        "Width": 1,
        "Height": 1,
        "Name": "Nameless Ring",
        "InheritsFrom": "Metadata/Items/Rings/AbstractRing",
        "DropLevel": 68,
        "FlavourTextKey": null,
        "Implicit_ModsKeys": [
            24170
        ],
        "SizeOnGround": 1,
        "SoundEffect": null,
        "TagsKeys": [
            33
        ],
        "ModDomain": 1,
        "SiteVisibility": 1,
        "ItemVisualIdentity": 7366,
        "HASH32": 1623932284,
        "VendorRecipe_AchievementItems": [],
        "Inflection": "",
        "Equip_AchievementItemsKey": null,
        "IsCorrupted": false,
        "Identify_AchievementItems": [],
        "IdentifyMagic_AchievementItems": [],
        "FragmentBaseItemTypesKey": null,
        "Unknown24": false,
        "Unknown25": null,
        "Unknown26": null,
        "Unknown27": false,
        "TradeMarketCategory": null,
        "Unmodifiable": false,
        "Achievement": [
            10450
        ],
        "Unknown31": [],
        "IgnoreQuantBonus": false,
        "Unknown33": false
    },
    {
        "_rid": 5781,
        "Id": "Metadata/Items/Rings/RingVictor1",
        "ItemClassesKey": 5,
        "Width": 1,
        "Height": 1,
        "Name": "Jet Ring",
        "InheritsFrom": "Metadata/Items/Rings/AbstractRing",
        "DropLevel": 15,
        "FlavourTextKey": null,
        "Implicit_ModsKeys": [
            7573
        ],
        "SizeOnGround": 1,
        "SoundEffect": null,
        "TagsKeys": [
            33,
            709
        ],
        "ModDomain": 1,
        "SiteVisibility": 0,
        "ItemVisualIdentity": 11347,
        "HASH32": -507420189,
        "VendorRecipe_AchievementItems": [],
        "Inflection": "",
        "Equip_AchievementItemsKey": null,
        "IsCorrupted": false,
        "Identify_AchievementItems": [],
        "IdentifyMagic_AchievementItems": [],
        "FragmentBaseItemTypesKey": null,
        "Unknown24": false,
        "Unknown25": null,
        "Unknown26": null,
        "Unknown27": false,
        "TradeMarketCategory": null,
        "Unmodifiable": false,
        "Achievement": [],
        "Unknown31": [],
        "IgnoreQuantBonus": false,
        "Unknown33": false
    },
    {
        "_rid": 5782,
        "Id": "Metadata/Items/Rings/RingAtlas1",
        "ItemClassesKey": 5,
        "Width": 1,
        "Height": 1,
        "Name": "Steel Ring",
        "InheritsFrom": "Metadata/Items/Rings/AbstractRing",
        "DropLevel": 78,
        "FlavourTextKey": null,
        "Implicit_ModsKeys": [
            798
        ],
        "SizeOnGround": 1,
        "SoundEffect": null,
        "TagsKeys": [
            33,
            177,
            178
        ],
        "ModDomain": 1,
        "SiteVisibility": 1,
        "ItemVisualIdentity": 7368,
        "HASH32": -583193006,
        "VendorRecipe_AchievementItems": [],
        "Inflection": "",
        "Equip_AchievementItemsKey": null,
        "IsCorrupted": false,
        "Identify_AchievementItems": [],
        "IdentifyMagic_AchievementItems": [],
        "FragmentBaseItemTypesKey": null,
        "Unknown24": false,
        "Unknown25": null,
        "Unknown26": null,
        "Unknown27": false,
        "TradeMarketCategory": null,
        "Unmodifiable": false,
        "Achievement": [
            10451
        ],
        "Unknown31": [],
        "IgnoreQuantBonus": false,
        "Unknown33": false
    },
    {
        "_rid": 5783,
        "Id": "Metadata/Items/Rings/RingAtlas2",
        "ItemClassesKey": 5,
        "Width": 1,
        "Height": 1,
        "Name": "Opal Ring",
        "InheritsFrom": "Metadata/Items/Rings/AbstractRing",
        "DropLevel": 78,
        "FlavourTextKey": null,
        "Implicit_ModsKeys": [
            1173
        ],
        "SizeOnGround": 1,
        "SoundEffect": null,
        "TagsKeys": [
            33,
            177,
            179
        ],
        "ModDomain": 1,
        "SiteVisibility": 1,
        "ItemVisualIdentity": 7369,
        "HASH32": -469808178,
        "VendorRecipe_AchievementItems": [],
        "Inflection": "",
        "Equip_AchievementItemsKey": null,
        "IsCorrupted": false,
        "Identify_AchievementItems": [],
        "IdentifyMagic_AchievementItems": [],
        "FragmentBaseItemTypesKey": null,
        "Unknown24": false,
        "Unknown25": null,
        "Unknown26": null,
        "Unknown27": false,
        "TradeMarketCategory": null,
        "Unmodifiable": false,
        "Achievement": [
            10451
        ],
        "Unknown31": [],
        "IgnoreQuantBonus": false,
        "Unknown33": false
    },
    {
        "_rid": 5784,
        "Id": "Metadata/Items/Rings/RingAtlas3",
        "ItemClassesKey": 5,
        "Width": 1,
        "Height": 1,
        "Name": "Vermillion Ring",
        "InheritsFrom": "Metadata/Items/Rings/AbstractRing",
        "DropLevel": 80,
        "FlavourTextKey": null,
        "Implicit_ModsKeys": [
            4572
        ],
        "SizeOnGround": 1,
        "SoundEffect": null,
        "TagsKeys": [
            33,
            177,
            449
        ],
        "ModDomain": 1,
        "SiteVisibility": 1,
        "ItemVisualIdentity": 7370,
        "HASH32": -1768478825,
        "VendorRecipe_AchievementItems": [],
        "Inflection": "",
        "Equip_AchievementItemsKey": null,
        "IsCorrupted": false,
        "Identify_AchievementItems": [],
        "IdentifyMagic_AchievementItems": [],
        "FragmentBaseItemTypesKey": null,
        "Unknown24": false,
        "Unknown25": null,
        "Unknown26": null,
        "Unknown27": false,
        "TradeMarketCategory": null,
        "Unmodifiable": false,
        "Achievement": [
            10451
        ],
        "Unknown31": [],
        "IgnoreQuantBonus": false,
        "Unknown33": false
    },
    {
        "_rid": 5785,
        "Id": "Metadata/Items/Rings/RingAtlas4",
        "ItemClassesKey": 5,
        "Width": 1,
        "Height": 1,
        "Name": "Cerulean Ring",
        "InheritsFrom": "Metadata/Items/Rings/AbstractRing",
        "DropLevel": 80,
        "FlavourTextKey": null,
        "Implicit_ModsKeys": [
            4536
        ],
        "SizeOnGround": 1,
        "SoundEffect": null,
        "TagsKeys": [
            33,
            177,
            450
        ],
        "ModDomain": 1,
        "SiteVisibility": 1,
        "ItemVisualIdentity": 7371,
        "HASH32": 43084961,
        "VendorRecipe_AchievementItems": [],
        "Inflection": "",
        "Equip_AchievementItemsKey": null,
        "IsCorrupted": false,
        "Identify_AchievementItems": [],
        "IdentifyMagic_AchievementItems": [],
        "FragmentBaseItemTypesKey": null,
        "Unknown24": false,
        "Unknown25": null,
        "Unknown26": null,
        "Unknown27": false,
        "TradeMarketCategory": null,
        "Unmodifiable": false,
        "Achievement": [
            10451
        ],
        "Unknown31": [],
        "IgnoreQuantBonus": false,
        "Unknown33": false
    },
    {
        "_rid": 5786,
        "Id": "Metadata/Items/Rings/RingAtlas5",
        "ItemClassesKey": 5,
        "Width": 1,
        "Height": 1,
        "Name": "Iolite Ring",
        "InheritsFrom": "Metadata/Items/Rings/AbstractRing",
        "DropLevel": 78,
        "FlavourTextKey": null,
        "Implicit_ModsKeys": [
            8539
        ],
        "SizeOnGround": 1,
        "SoundEffect": null,
        "TagsKeys": [
            33,
            177,
            702
        ],
        "ModDomain": 1,
        "SiteVisibility": 1,
        "ItemVisualIdentity": 7372,
        "HASH32": 30469034,
        "VendorRecipe_AchievementItems": [],
        "Inflection": "",
        "Equip_AchievementItemsKey": null,
        "IsCorrupted": false,
        "Identify_AchievementItems": [],
        "IdentifyMagic_AchievementItems": [],
        "FragmentBaseItemTypesKey": null,
        "Unknown24": false,
        "Unknown25": null,
        "Unknown26": null,
        "Unknown27": false,
        "TradeMarketCategory": null,
        "Unmodifiable": false,
        "Achievement": [
            10451
        ],
        "Unknown31": [],
        "IgnoreQuantBonus": false,
        "Unknown33": false
    },
    {
        "_rid": 5787,
        "Id": "Metadata/Items/Rings/MirrorRing",
        "ItemClassesKey": 5,
        "Width": 1,
        "Height": 1,
        "Name": "Ring",
        "InheritsFrom": "Metadata/Items/Rings/AbstractRing",
        "DropLevel": 1,
        "FlavourTextKey": null,
        "Implicit_ModsKeys": [],
        "SizeOnGround": 1,
        "SoundEffect": null,
        "TagsKeys": [
            33
        ],
        "ModDomain": 1,
        "SiteVisibility": 1,
        "ItemVisualIdentity": 7374,
        "HASH32": 207622696,
        "VendorRecipe_AchievementItems": [],
        "Inflection": "",
        "Equip_AchievementItemsKey": null,
        "IsCorrupted": false,
        "Identify_AchievementItems": [],
        "IdentifyMagic_AchievementItems": [],
        "FragmentBaseItemTypesKey": null,
        "Unknown24": false,
        "Unknown25": null,
        "Unknown26": null,
        "Unknown27": false,
        "TradeMarketCategory": null,
        "Unmodifiable": false,
        "Achievement": [],
        "Unknown31": [],
        "IgnoreQuantBonus": false,
        "Unknown33": false
    },
    {
        "_rid": 5788,
        "Id": "Metadata/Items/Rings/BreachRing",
        "ItemClassesKey": 5,
        "Width": 1,
        "Height": 1,
        "Name": "Breach Ring",
        "InheritsFrom": "Metadata/Items/Rings/AbstractRing",
        "DropLevel": 1,
        "FlavourTextKey": null,
        "Implicit_ModsKeys": [
            13237
        ],
        "SizeOnGround": 1,
        "SoundEffect": null,
        "TagsKeys": [
            33
        ],
        "ModDomain": 1,
        "SiteVisibility": 1,
        "ItemVisualIdentity": 7373,
        "HASH32": -1784046448,
        "VendorRecipe_AchievementItems": [],
        "Inflection": "",
        "Equip_AchievementItemsKey": null,
        "IsCorrupted": true,
        "Identify_AchievementItems": [],
        "IdentifyMagic_AchievementItems": [],
        "FragmentBaseItemTypesKey": null,
        "Unknown24": false,
        "Unknown25": null,
        "Unknown26": null,
        "Unknown27": false,
        "TradeMarketCategory": null,
        "Unmodifiable": false,
        "Achievement": [],
        "Unknown31": [],
        "IgnoreQuantBonus": false,
        "Unknown33": false
    },
    {
        "_rid": 5789,
        "Id": "Metadata/Items/Rings/RingRoyale1",
        "ItemClassesKey": 5,
        "Width": 1,
        "Height": 1,
        "Name": "Opal Ring",
        "InheritsFrom": "Metadata/Items/Rings/AbstractRing",
        "DropLevel": 2,
        "FlavourTextKey": null,
        "Implicit_ModsKeys": [
            1174
        ],
        "SizeOnGround": 1,
        "SoundEffect": null,
        "TagsKeys": [
            33
        ],
        "ModDomain": 1,
        "SiteVisibility": 0,
        "ItemVisualIdentity": 7369,
        "HASH32": 335960361,
        "VendorRecipe_AchievementItems": [],
        "Inflection": "",
        "Equip_AchievementItemsKey": null,
        "IsCorrupted": false,
        "Identify_AchievementItems": [],
        "IdentifyMagic_AchievementItems": [],
        "FragmentBaseItemTypesKey": null,
        "Unknown24": false,
        "Unknown25": null,
        "Unknown26": null,
        "Unknown27": false,
        "TradeMarketCategory": null,
        "Unmodifiable": false,
        "Achievement": [],
        "Unknown31": [],
        "IgnoreQuantBonus": false,
        "Unknown33": false
    },
    {
        "_rid": 5790,
        "Id": "Metadata/Items/Rings/RingRoyale2",
        "ItemClassesKey": 5,
        "Width": 1,
        "Height": 1,
        "Name": "Prismatic Ring",
        "InheritsFrom": "Metadata/Items/Rings/AbstractRing",
        "DropLevel": 2,
        "FlavourTextKey": null,
        "Implicit_ModsKeys": [
            3455
        ],
        "SizeOnGround": 1,
        "SoundEffect": null,
        "TagsKeys": [
            33
        ],
        "ModDomain": 1,
        "SiteVisibility": 0,
        "ItemVisualIdentity": 7346,
        "HASH32": -120301954,
        "VendorRecipe_AchievementItems": [],
        "Inflection": "",
        "Equip_AchievementItemsKey": null,
        "IsCorrupted": false,
        "Identify_AchievementItems": [],
        "IdentifyMagic_AchievementItems": [],
        "FragmentBaseItemTypesKey": null,
        "Unknown24": false,
        "Unknown25": null,
        "Unknown26": null,
        "Unknown27": false,
        "TradeMarketCategory": null,
        "Unmodifiable": false,
        "Achievement": [],
        "Unknown31": [],
        "IgnoreQuantBonus": false,
        "Unknown33": false
    },
    {
        "_rid": 5791,
        "Id": "Metadata/Items/Rings/RingRoyale3",
        "ItemClassesKey": 5,
        "Width": 1,
        "Height": 1,
        "Name": "Diamond Ring",
        "InheritsFrom": "Metadata/Items/Rings/AbstractRing",
        "DropLevel": 2,
        "FlavourTextKey": null,
        "Implicit_ModsKeys": [
            3093
        ],
        "SizeOnGround": 1,
        "SoundEffect": null,
        "TagsKeys": [
            33
        ],
        "ModDomain": 1,
        "SiteVisibility": 0,
        "ItemVisualIdentity": 7349,
        "HASH32": 1953679860,
        "VendorRecipe_AchievementItems": [],
        "Inflection": "",
        "Equip_AchievementItemsKey": null,
        "IsCorrupted": false,
        "Identify_AchievementItems": [],
        "IdentifyMagic_AchievementItems": [],
        "FragmentBaseItemTypesKey": null,
        "Unknown24": false,
        "Unknown25": null,
        "Unknown26": null,
        "Unknown27": false,
        "TradeMarketCategory": null,
        "Unmodifiable": false,
        "Achievement": [],
        "Unknown31": [],
        "IgnoreQuantBonus": false,
        "Unknown33": false
    },
    {
        "_rid": 5792,
        "Id": "Metadata/Items/Rings/RingRoyale4",
        "ItemClassesKey": 5,
        "Width": 1,
        "Height": 1,
        "Name": "Paua Ring",
        "InheritsFrom": "Metadata/Items/Rings/AbstractRing",
        "DropLevel": 2,
        "FlavourTextKey": null,
        "Implicit_ModsKeys": [
            563
        ],
        "SizeOnGround": 1,
        "SoundEffect": null,
        "TagsKeys": [
            33
        ],
        "ModDomain": 1,
        "SiteVisibility": 0,
        "ItemVisualIdentity": 7341,
        "HASH32": -1429425884,
        "VendorRecipe_AchievementItems": [],
        "Inflection": "",
        "Equip_AchievementItemsKey": null,
        "IsCorrupted": false,
        "Identify_AchievementItems": [],
        "IdentifyMagic_AchievementItems": [],
        "FragmentBaseItemTypesKey": null,
        "Unknown24": false,
        "Unknown25": null,
        "Unknown26": null,
        "Unknown27": false,
        "TradeMarketCategory": null,
        "Unmodifiable": false,
        "Achievement": [],
        "Unknown31": [],
        "IgnoreQuantBonus": false,
        "Unknown33": false
    },
    {
        "_rid": 11671,
        "Id": "Metadata/Items/Rings/RingGamble",
        "ItemClassesKey": 61,
        "Width": 1,
        "Height": 1,
        "Name": "Random Ring",
        "InheritsFrom": "Metadata/Items/Item",
        "DropLevel": 2,
        "FlavourTextKey": null,
        "Implicit_ModsKeys": [],
        "SizeOnGround": 3,
        "SoundEffect": null,
        "TagsKeys": [],
        "ModDomain": 1,
        "SiteVisibility": 0,
        "ItemVisualIdentity": 14495,
        "HASH32": 587652089,
        "VendorRecipe_AchievementItems": [],
        "Inflection": "",
        "Equip_AchievementItemsKey": null,
        "IsCorrupted": false,
        "Identify_AchievementItems": [],
        "IdentifyMagic_AchievementItems": [],
        "FragmentBaseItemTypesKey": null,
        "Unknown24": false,
        "Unknown25": null,
        "Unknown26": null,
        "Unknown27": true,
        "TradeMarketCategory": null,
        "Unmodifiable": false,
        "Achievement": [],
        "Unknown31": [],
        "IgnoreQuantBonus": false,
        "Unknown33": false
    }
]