[
    {
        "_rid": 5646,
        "Id": "Metadata/Items/Weapons/TwoHandWeapons/Staves/Staff1",
        "ItemClassesKey": 14,
        "Width": 1,
        "Height": 4,
        "Name": "Gnarled Branch",
        "InheritsFrom": "Metadata/Items/Weapons/TwoHandWeapons/Staves/AbstractStaff",
        "DropLevel": 4,
        "FlavourTextKey": null,
        "Implicit_ModsKeys": [
            1137
        ],
        "SizeOnGround": 3,
        "SoundEffect": null,
        "TagsKeys": [
            165
        ],
        "ModDomain": 1,
        "SiteVisibility": 1,
        "ItemVisualIdentity": 7301,
        "HASH32": 1223503515,
        "VendorRecipe_AchievementItems": [],
        "Inflection": "",
        "Equip_AchievementItemsKey": null,
        "IsCorrupted": false,
        "Identify_AchievementItems": [],
        "IdentifyMagic_AchievementItems": [],
        "FragmentBaseItemTypesKey": null,
        "Unknown24": false,
        "Unknown25": null,
        "Unknown26": null,
        "Unknown27": false,
        "TradeMarketCategory": null,
        "Unmodifiable": false,
        "Achievement": [],
        "Unknown31": [],
        "IgnoreQuantBonus": false,
        "Unknown33": false
    },
    {
        "_rid": 5647,
        "Id": "Metadata/Items/Weapons/TwoHandWeapons/Staves/Staff2",
        "ItemClassesKey": 14,
        "Width": 2,
        "Height": 4,
        "Name": "Primitive Staff",
        "InheritsFrom": "Metadata/Items/Weapons/TwoHandWeapons/Staves/AbstractStaff",
        "DropLevel": 9,
        "FlavourTextKey": null,
        "Implicit_ModsKeys": [
            1137
        ],
        "SizeOnGround": 3,
        "SoundEffect": null,
        "TagsKeys": [],
        "ModDomain": 1,
        "SiteVisibility": 1,
        "ItemVisualIdentity": 7302,
        "HASH32": -428233432,
        "VendorRecipe_AchievementItems": [],
        "Inflection": "",
        "Equip_AchievementItemsKey": null,
        "IsCorrupted": false,
        "Identify_AchievementItems": [],
        "IdentifyMagic_AchievementItems": [],
        "FragmentBaseItemTypesKey": null,
        "Unknown24": false,
        "Unknown25": null,
        "Unknown26": null,
        "Unknown27": false,
        "TradeMarketCategory": null,
        "Unmodifiable": false,
        "Achievement": [],
        "Unknown31": [],
        "IgnoreQuantBonus": false,
        "Unknown33": false
    },
    {
        "_rid": 5648,
        "Id": "Metadata/Items/Weapons/TwoHandWeapons/Staves/Staff3",
        "ItemClassesKey": 14,
        "Width": 2,
        "Height": 4,
        "Name": "Long Staff",
        "InheritsFrom": "Metadata/Items/Weapons/TwoHandWeapons/Staves/AbstractStaff",
        "DropLevel": 18,
        "FlavourTextKey": null,
        "Implicit_ModsKeys": [
            1137
        ],
        "SizeOnGround": 3,
        "SoundEffect": null,
        "TagsKeys": [],
        "ModDomain": 1,
        "SiteVisibility": 1,
        "ItemVisualIdentity": 7303,
        "HASH32": 1252462495,
        "VendorRecipe_AchievementItems": [],
        "Inflection": "",
        "Equip_AchievementItemsKey": null,
        "IsCorrupted": false,
        "Identify_AchievementItems": [],
        "IdentifyMagic_AchievementItems": [],
        "FragmentBaseItemTypesKey": null,
        "Unknown24": false,
        "Unknown25": null,
        "Unknown26": null,
        "Unknown27": false,
        "TradeMarketCategory": null,
        "Unmodifiable": false,
        "Achievement": [],
        "Unknown31": [],
        "IgnoreQuantBonus": false,
        "Unknown33": false
    },
    {
        "_rid": 5649,
        "Id": "Metadata/Items/Weapons/TwoHandWeapons/Staves/Staff4",
        "ItemClassesKey": 57,
        "Width": 2,
        "Height": 4,
        "Name": "Iron Staff",
        "InheritsFrom": "Metadata/Items/Weapons/TwoHandWeapons/Staves/AbstractWarstaff",
        "DropLevel": 13,
        "FlavourTextKey": null,
        "Implicit_ModsKeys": [
            1127
        ],
        "SizeOnGround": 3,
        "SoundEffect": null,
        "TagsKeys": [
            566
        ],
        "ModDomain": 1,
        "SiteVisibility": 1,
        "ItemVisualIdentity": 7304,
        "HASH32": -525178737,
        "VendorRecipe_AchievementItems": [],
        "Inflection": "",
        "Equip_AchievementItemsKey": null,
        "IsCorrupted": false,
        "Identify_AchievementItems": [],
        "IdentifyMagic_AchievementItems": [],
        "FragmentBaseItemTypesKey": null,
        "Unknown24": false,
        "Unknown25": null,
        "Unknown26": null,
        "Unknown27": false,
        "TradeMarketCategory": null,
        "Unmodifiable": false,
        "Achievement": [],
        "Unknown31": [],
        "IgnoreQuantBonus": false,
        "Unknown33": false
    },
    {
        "_rid": 5650,
        "Id": "Metadata/Items/Weapons/TwoHandWeapons/Staves/Staff5",
        "ItemClassesKey": 57,
        "Width": 2,
        "Height": 4,
        "Name": "Coiled Staff",
        "InheritsFrom": "Metadata/Items/Weapons/TwoHandWeapons/Staves/AbstractWarstaff",
        "DropLevel": 23,
        "FlavourTextKey": null,
        "Implicit_ModsKeys": [
            1127
        ],
        "SizeOnGround": 3,
        "SoundEffect": null,
        "TagsKeys": [
            566
        ],
        "ModDomain": 1,
        "SiteVisibility": 1,
        "ItemVisualIdentity": 7305,
        "HASH32": 2049886524,
        "VendorRecipe_AchievementItems": [],
        "Inflection": "",
        "Equip_AchievementItemsKey": null,
        "IsCorrupted": false,
        "Identify_AchievementItems": [],
        "IdentifyMagic_AchievementItems": [],
        "FragmentBaseItemTypesKey": null,
        "Unknown24": false,
        "Unknown25": null,
        "Unknown26": null,
        "Unknown27": false,
        "TradeMarketCategory": null,
        "Unmodifiable": false,
        "Achievement": [],
        "Unknown31": [],
        "IgnoreQuantBonus": false,
        "Unknown33": false
    },
    {
        "_rid": 5651,
        "Id": "Metadata/Items/Weapons/TwoHandWeapons/Staves/Staff6",
        "ItemClassesKey": 14,
        "Width": 2,
        "Height": 4,
        "Name": "Royal Staff",
        "InheritsFrom": "Metadata/Items/Weapons/TwoHandWeapons/Staves/AbstractStaff",
        "DropLevel": 28,
        "FlavourTextKey": null,
        "Implicit_ModsKeys": [
            1137
        ],
        "SizeOnGround": 3,
        "SoundEffect": null,
        "TagsKeys": [],
        "ModDomain": 1,
        "SiteVisibility": 1,
        "ItemVisualIdentity": 7306,
        "HASH32": -1233147515,
        "VendorRecipe_AchievementItems": [],
        "Inflection": "",
        "Equip_AchievementItemsKey": null,
        "IsCorrupted": false,
        "Identify_AchievementItems": [],
        "IdentifyMagic_AchievementItems": [],
        "FragmentBaseItemTypesKey": null,
        "Unknown24": false,
        "Unknown25": null,
        "Unknown26": null,
        "Unknown27": false,
        "TradeMarketCategory": null,
        "Unmodifiable": false,
        "Achievement": [],
        "Unknown31": [],
        "IgnoreQuantBonus": false,
        "Unknown33": false
    },
    {
        "_rid": 5652,
        "Id": "Metadata/Items/Weapons/TwoHandWeapons/Staves/Staff7",
        "ItemClassesKey": 57,
        "Width": 2,
        "Height": 4,
        "Name": "Vile Staff",
        "InheritsFrom": "Metadata/Items/Weapons/TwoHandWeapons/Staves/AbstractWarstaff",
        "DropLevel": 33,
        "FlavourTextKey": null,
        "Implicit_ModsKeys": [
            1127
        ],
        "SizeOnGround": 3,
        "SoundEffect": null,
        "TagsKeys": [
            566
        ],
        "ModDomain": 1,
        "SiteVisibility": 1,
        "ItemVisualIdentity": 7307,
        "HASH32": 500629341,
        "VendorRecipe_AchievementItems": [],
        "Inflection": "",
        "Equip_AchievementItemsKey": null,
        "IsCorrupted": false,
        "Identify_AchievementItems": [],
        "IdentifyMagic_AchievementItems": [],
        "FragmentBaseItemTypesKey": null,
        "Unknown24": false,
        "Unknown25": null,
        "Unknown26": null,
        "Unknown27": false,
        "TradeMarketCategory": null,
        "Unmodifiable": false,
        "Achievement": [],
        "Unknown31": [],
        "IgnoreQuantBonus": false,
        "Unknown33": false
    },
    {
        "_rid": 5653,
        "Id": "Metadata/Items/Weapons/TwoHandWeapons/Staves/StaffM1",
        "ItemClassesKey": 14,
        "Width": 2,
        "Height": 4,
        "Name": "Crescent Staff",
        "InheritsFrom": "Metadata/Items/Weapons/TwoHandWeapons/Staves/AbstractStaff",
        "DropLevel": 36,
        "FlavourTextKey": null,
        "Implicit_ModsKeys": [
            3082
        ],
        "SizeOnGround": 3,
        "SoundEffect": null,
        "TagsKeys": [
            33,
            173
        ],
        "ModDomain": 1,
        "SiteVisibility": 1,
        "ItemVisualIdentity": 7308,
        "HASH32": -272638100,
        "VendorRecipe_AchievementItems": [],
        "Inflection": "",
        "Equip_AchievementItemsKey": 2518,
        "IsCorrupted": false,
        "Identify_AchievementItems": [],
        "IdentifyMagic_AchievementItems": [],
        "FragmentBaseItemTypesKey": null,
        "Unknown24": false,
        "Unknown25": null,
        "Unknown26": null,
        "Unknown27": false,
        "TradeMarketCategory": null,
        "Unmodifiable": false,
        "Achievement": [
            9387
        ],
        "Unknown31": [],
        "IgnoreQuantBonus": false,
        "Unknown33": false
    },
    {
        "_rid": 5654,
        "Id": "Metadata/Items/Weapons/TwoHandWeapons/Staves/Staff8",
        "ItemClassesKey": 14,
        "Width": 2,
        "Height": 4,
        "Name": "Woodful Staff",
        "InheritsFrom": "Metadata/Items/Weapons/TwoHandWeapons/Staves/AbstractStaff",
        "DropLevel": 37,
        "FlavourTextKey": null,
        "Implicit_ModsKeys": [
            1138
        ],
        "SizeOnGround": 3,
        "SoundEffect": null,
        "TagsKeys": [],
        "ModDomain": 1,
        "SiteVisibility": 1,
        "ItemVisualIdentity": 7302,
        "HASH32": -827148946,
        "VendorRecipe_AchievementItems": [],
        "Inflection": "",
        "Equip_AchievementItemsKey": null,
        "IsCorrupted": false,
        "Identify_AchievementItems": [],
        "IdentifyMagic_AchievementItems": [],
        "FragmentBaseItemTypesKey": null,
        "Unknown24": false,
        "Unknown25": null,
        "Unknown26": null,
        "Unknown27": false,
        "TradeMarketCategory": null,
        "Unmodifiable": false,
        "Achievement": [],
        "Unknown31": [],
        "IgnoreQuantBonus": false,
        "Unknown33": false
    },
    {
        "_rid": 5655,
        "Id": "Metadata/Items/Weapons/TwoHandWeapons/Staves/Staff9",
        "ItemClassesKey": 14,
        "Width": 2,
        "Height": 4,
        "Name": "Quarterstaff",
        "InheritsFrom": "Metadata/Items/Weapons/TwoHandWeapons/Staves/AbstractStaff",
        "DropLevel": 45,
        "FlavourTextKey": null,
        "Implicit_ModsKeys": [
            1138
        ],
        "SizeOnGround": 3,
        "SoundEffect": null,
        "TagsKeys": [],
        "ModDomain": 1,
        "SiteVisibility": 1,
        "ItemVisualIdentity": 7303,
        "HASH32": 403848484,
        "VendorRecipe_AchievementItems": [],
        "Inflection": "",
        "Equip_AchievementItemsKey": null,
        "IsCorrupted": false,
        "Identify_AchievementItems": [],
        "IdentifyMagic_AchievementItems": [],
        "FragmentBaseItemTypesKey": null,
        "Unknown24": false,
        "Unknown25": null,
        "Unknown26": null,
        "Unknown27": false,
        "TradeMarketCategory": null,
        "Unmodifiable": false,
        "Achievement": [],
        "Unknown31": [],
        "IgnoreQuantBonus": false,
        "Unknown33": false
    },
    {
        "_rid": 5656,
        "Id": "Metadata/Items/Weapons/TwoHandWeapons/Staves/Staff10",
        "ItemClassesKey": 57,
        "Width": 2,
        "Height": 4,
        "Name": "Military Staff",
        "InheritsFrom": "Metadata/Items/Weapons/TwoHandWeapons/Staves/AbstractWarstaff",
        "DropLevel": 41,
        "FlavourTextKey": null,
        "Implicit_ModsKeys": [
            1128
        ],
        "SizeOnGround": 3,
        "SoundEffect": null,
        "TagsKeys": [
            566
        ],
        "ModDomain": 1,
        "SiteVisibility": 1,
        "ItemVisualIdentity": 7304,
        "HASH32": 269559024,
        "VendorRecipe_AchievementItems": [],
        "Inflection": "",
        "Equip_AchievementItemsKey": null,
        "IsCorrupted": false,
        "Identify_AchievementItems": [],
        "IdentifyMagic_AchievementItems": [],
        "FragmentBaseItemTypesKey": null,
        "Unknown24": false,
        "Unknown25": null,
        "Unknown26": null,
        "Unknown27": false,
        "TradeMarketCategory": null,
        "Unmodifiable": false,
        "Achievement": [],
        "Unknown31": [],
        "IgnoreQuantBonus": false,
        "Unknown33": false
    },
    {
        "_rid": 5657,
        "Id": "Metadata/Items/Weapons/TwoHandWeapons/Staves/Staff11",
        "ItemClassesKey": 57,
        "Width": 2,
        "Height": 4,
        "Name": "Serpentine Staff",
        "InheritsFrom": "Metadata/Items/Weapons/TwoHandWeapons/Staves/AbstractWarstaff",
        "DropLevel": 49,
        "FlavourTextKey": null,
        "Implicit_ModsKeys": [
            1128
        ],
        "SizeOnGround": 3,
        "SoundEffect": null,
        "TagsKeys": [
            566
        ],
        "ModDomain": 1,
        "SiteVisibility": 1,
        "ItemVisualIdentity": 7305,
        "HASH32": -1498275601,
        "VendorRecipe_AchievementItems": [],
        "Inflection": "",
        "Equip_AchievementItemsKey": null,
        "IsCorrupted": false,
        "Identify_AchievementItems": [],
        "IdentifyMagic_AchievementItems": [],
        "FragmentBaseItemTypesKey": null,
        "Unknown24": false,
        "Unknown25": null,
        "Unknown26": null,
        "Unknown27": false,
        "TradeMarketCategory": null,
        "Unmodifiable": false,
        "Achievement": [],
        "Unknown31": [],
        "IgnoreQuantBonus": false,
        "Unknown33": false
    },
    {
        "_rid": 5658,
        "Id": "Metadata/Items/Weapons/TwoHandWeapons/Staves/Staff12",
        "ItemClassesKey": 14,
        "Width": 2,
        "Height": 4,
        "Name": "Highborn Staff",
        "InheritsFrom": "Metadata/Items/Weapons/TwoHandWeapons/Staves/AbstractStaff",
        "DropLevel": 52,
        "FlavourTextKey": null,
        "Implicit_ModsKeys": [
            1138
        ],
        "SizeOnGround": 3,
        "SoundEffect": null,
        "TagsKeys": [],
        "ModDomain": 1,
        "SiteVisibility": 1,
        "ItemVisualIdentity": 7306,
        "HASH32": 473547360,
        "VendorRecipe_AchievementItems": [],
        "Inflection": "",
        "Equip_AchievementItemsKey": null,
        "IsCorrupted": false,
        "Identify_AchievementItems": [],
        "IdentifyMagic_AchievementItems": [],
        "FragmentBaseItemTypesKey": null,
        "Unknown24": false,
        "Unknown25": null,
        "Unknown26": null,
        "Unknown27": false,
        "TradeMarketCategory": null,
        "Unmodifiable": false,
        "Achievement": [],
        "Unknown31": [],
        "IgnoreQuantBonus": false,
        "Unknown33": false
    },
    {
        "_rid": 5659,
        "Id": "Metadata/Items/Weapons/TwoHandWeapons/Staves/Staff13",
        "ItemClassesKey": 57,
        "Width": 2,
        "Height": 4,
        "Name": "Foul Staff",
        "InheritsFrom": "Metadata/Items/Weapons/TwoHandWeapons/Staves/AbstractWarstaff",
        "DropLevel": 55,
        "FlavourTextKey": null,
        "Implicit_ModsKeys": [
            1128
        ],
        "SizeOnGround": 3,
        "SoundEffect": null,
        "TagsKeys": [
            566
        ],
        "ModDomain": 1,
        "SiteVisibility": 1,
        "ItemVisualIdentity": 7307,
        "HASH32": 796883108,
        "VendorRecipe_AchievementItems": [],
        "Inflection": "",
        "Equip_AchievementItemsKey": null,
        "IsCorrupted": false,
        "Identify_AchievementItems": [],
        "IdentifyMagic_AchievementItems": [],
        "FragmentBaseItemTypesKey": null,
        "Unknown24": false,
        "Unknown25": null,
        "Unknown26": null,
        "Unknown27": false,
        "TradeMarketCategory": null,
        "Unmodifiable": false,
        "Achievement": [],
        "Unknown31": [],
        "IgnoreQuantBonus": false,
        "Unknown33": false
    },
    {
        "_rid": 5660,
        "Id": "Metadata/Items/Weapons/TwoHandWeapons/Staves/StaffM2",
        "ItemClassesKey": 14,
        "Width": 2,
        "Height": 4,
        "Name": "Moon Staff",
        "InheritsFrom": "Metadata/Items/Weapons/TwoHandWeapons/Staves/AbstractStaff",
        "DropLevel": 57,
        "FlavourTextKey": null,
        "Implicit_ModsKeys": [
            3082
        ],
        "SizeOnGround": 3,
        "SoundEffect": null,
        "TagsKeys": [
            33,
            173
        ],
        "ModDomain": 1,
        "SiteVisibility": 1,
        "ItemVisualIdentity": 7308,
        "HASH32": -292408269,
        "VendorRecipe_AchievementItems": [],
        "Inflection": "",
        "Equip_AchievementItemsKey": 2518,
        "IsCorrupted": false,
        "Identify_AchievementItems": [],
        "IdentifyMagic_AchievementItems": [],
        "FragmentBaseItemTypesKey": null,
        "Unknown24": false,
        "Unknown25": null,
        "Unknown26": null,
        "Unknown27": false,
        "TradeMarketCategory": null,
        "Unmodifiable": false,
        "Achievement": [
            9387
        ],
        "Unknown31": [],
        "IgnoreQuantBonus": false,
        "Unknown33": false
    },
    {
        "_rid": 5661,
        "Id": "Metadata/Items/Weapons/TwoHandWeapons/Staves/Staff14",
        "ItemClassesKey": 14,
        "Width": 2,
        "Height": 4,
        "Name": "Primordial Staff",
        "InheritsFrom": "Metadata/Items/Weapons/TwoHandWeapons/Staves/AbstractStaff",
        "DropLevel": 58,
        "FlavourTextKey": null,
        "Implicit_ModsKeys": [
            1139
        ],
        "SizeOnGround": 3,
        "SoundEffect": null,
        "TagsKeys": [],
        "ModDomain": 1,
        "SiteVisibility": 1,
        "ItemVisualIdentity": 7302,
        "HASH32": -1914061947,
        "VendorRecipe_AchievementItems": [],
        "Inflection": "",
        "Equip_AchievementItemsKey": null,
        "IsCorrupted": false,
        "Identify_AchievementItems": [],
        "IdentifyMagic_AchievementItems": [],
        "FragmentBaseItemTypesKey": null,
        "Unknown24": false,
        "Unknown25": null,
        "Unknown26": null,
        "Unknown27": false,
        "TradeMarketCategory": null,
        "Unmodifiable": false,
        "Achievement": [],
        "Unknown31": [],
        "IgnoreQuantBonus": false,
        "Unknown33": false
    },
    {
        "_rid": 5662,
        "Id": "Metadata/Items/Weapons/TwoHandWeapons/Staves/Staff15",
        "ItemClassesKey": 14,
        "Width": 2,
        "Height": 4,
        "Name": "Lathi",
        "InheritsFrom": "Metadata/Items/Weapons/TwoHandWeapons/Staves/AbstractStaff",
        "DropLevel": 62,
        "FlavourTextKey": null,
        "Implicit_ModsKeys": [
            1139
        ],
        "SizeOnGround": 3,
        "SoundEffect": null,
        "TagsKeys": [
            1049
        ],
        "ModDomain": 1,
        "SiteVisibility": 1,
        "ItemVisualIdentity": 7303,
        "HASH32": 690106669,
        "VendorRecipe_AchievementItems": [],
        "Inflection": "",
        "Equip_AchievementItemsKey": null,
        "IsCorrupted": false,
        "Identify_AchievementItems": [],
        "IdentifyMagic_AchievementItems": [],
        "FragmentBaseItemTypesKey": null,
        "Unknown24": false,
        "Unknown25": null,
        "Unknown26": null,
        "Unknown27": false,
        "TradeMarketCategory": null,
        "Unmodifiable": false,
        "Achievement": [],
        "Unknown31": [],
        "IgnoreQuantBonus": false,
        "Unknown33": false
    },
    {
        "_rid": 5663,
        "Id": "Metadata/Items/Weapons/TwoHandWeapons/Staves/Staff16",
        "ItemClassesKey": 57,
        "Width": 2,
        "Height": 4,
        "Name": "Ezomyte Staff",
        "InheritsFrom": "Metadata/Items/Weapons/TwoHandWeapons/Staves/AbstractWarstaff",
        "DropLevel": 60,
        "FlavourTextKey": null,
        "Implicit_ModsKeys": [
            1129
        ],
        "SizeOnGround": 3,
        "SoundEffect": null,
        "TagsKeys": [
            566,
            1049
        ],
        "ModDomain": 1,
        "SiteVisibility": 1,
        "ItemVisualIdentity": 7304,
        "HASH32": -1318087019,
        "VendorRecipe_AchievementItems": [],
        "Inflection": "",
        "Equip_AchievementItemsKey": null,
        "IsCorrupted": false,
        "Identify_AchievementItems": [],
        "IdentifyMagic_AchievementItems": [],
        "FragmentBaseItemTypesKey": null,
        "Unknown24": false,
        "Unknown25": null,
        "Unknown26": null,
        "Unknown27": false,
        "TradeMarketCategory": null,
        "Unmodifiable": false,
        "Achievement": [],
        "Unknown31": [],
        "IgnoreQuantBonus": false,
        "Unknown33": false
    },
    {
        "_rid": 5664,
        "Id": "Metadata/Items/Weapons/TwoHandWeapons/Staves/Staff17",
        "ItemClassesKey": 57,
        "Width": 2,
        "Height": 4,
        "Name": "Maelstr\u00f6m Staff",
        "InheritsFrom": "Metadata/Items/Weapons/TwoHandWeapons/Staves/AbstractWarstaff",
        "DropLevel": 64,
        "FlavourTextKey": null,
        "Implicit_ModsKeys": [
            1129
        ],
        "SizeOnGround": 3,
        "SoundEffect": null,
        "TagsKeys": [
            566,
            1049
        ],
        "ModDomain": 1,
        "SiteVisibility": 1,
        "ItemVisualIdentity": 7305,
        "HASH32": 263430887,
        "VendorRecipe_AchievementItems": [],
        "Inflection": "",
        "Equip_AchievementItemsKey": null,
        "IsCorrupted": false,
        "Identify_AchievementItems": [],
        "IdentifyMagic_AchievementItems": [],
        "FragmentBaseItemTypesKey": null,
        "Unknown24": false,
        "Unknown25": null,
        "Unknown26": null,
        "Unknown27": false,
        "TradeMarketCategory": null,
        "Unmodifiable": false,
        "Achievement": [],
        "Unknown31": [],
        "IgnoreQuantBonus": false,
        "Unknown33": false
    },
    {
        "_rid": 5665,
        "Id": "Metadata/Items/Weapons/TwoHandWeapons/Staves/Staff18",
        "ItemClassesKey": 14,
        "Width": 2,
        "Height": 4,
        "Name": "Imperial Staff",
        "InheritsFrom": "Metadata/Items/Weapons/TwoHandWeapons/Staves/AbstractStaff",
        "DropLevel": 66,
        "FlavourTextKey": null,
        "Implicit_ModsKeys": [
            1139
        ],
        "SizeOnGround": 3,
        "SoundEffect": null,
        "TagsKeys": [
            1049
        ],
        "ModDomain": 1,
        "SiteVisibility": 1,
        "ItemVisualIdentity": 7306,
        "HASH32": 1640538772,
        "VendorRecipe_AchievementItems": [],
        "Inflection": "",
        "Equip_AchievementItemsKey": null,
        "IsCorrupted": false,
        "Identify_AchievementItems": [],
        "IdentifyMagic_AchievementItems": [],
        "FragmentBaseItemTypesKey": null,
        "Unknown24": false,
        "Unknown25": null,
        "Unknown26": null,
        "Unknown27": false,
        "TradeMarketCategory": null,
        "Unmodifiable": false,
        "Achievement": [],
        "Unknown31": [],
        "IgnoreQuantBonus": false,
        "Unknown33": false
    },
    {
        "_rid": 5666,
        "Id": "Metadata/Items/Weapons/TwoHandWeapons/Staves/Staff19",
        "ItemClassesKey": 57,
        "Width": 2,
        "Height": 4,
        "Name": "Judgement Staff",
        "InheritsFrom": "Metadata/Items/Weapons/TwoHandWeapons/Staves/AbstractWarstaff",
        "DropLevel": 68,
        "FlavourTextKey": null,
        "Implicit_ModsKeys": [
            1129
        ],
        "SizeOnGround": 3,
        "SoundEffect": null,
        "TagsKeys": [
            566,
            1049
        ],
        "ModDomain": 1,
        "SiteVisibility": 1,
        "ItemVisualIdentity": 7307,
        "HASH32": 316311209,
        "VendorRecipe_AchievementItems": [],
        "Inflection": "",
        "Equip_AchievementItemsKey": null,
        "IsCorrupted": false,
        "Identify_AchievementItems": [],
        "IdentifyMagic_AchievementItems": [],
        "FragmentBaseItemTypesKey": null,
        "Unknown24": false,
        "Unknown25": null,
        "Unknown26": null,
        "Unknown27": false,
        "TradeMarketCategory": null,
        "Unmodifiable": false,
        "Achievement": [],
        "Unknown31": [],
        "IgnoreQuantBonus": false,
        "Unknown33": false
    },
    {
        "_rid": 5667,
        "Id": "Metadata/Items/Weapons/TwoHandWeapons/Staves/StaffM3",
        "ItemClassesKey": 14,
        "Width": 2,
        "Height": 4,
        "Name": "Eclipse Staff",
        "InheritsFrom": "Metadata/Items/Weapons/TwoHandWeapons/Staves/AbstractStaff",
        "DropLevel": 70,
        "FlavourTextKey": null,
        "Implicit_ModsKeys": [
            3083
        ],
        "SizeOnGround": 3,
        "SoundEffect": null,
        "TagsKeys": [
            33,
            173
        ],
        "ModDomain": 1,
        "SiteVisibility": 1,
        "ItemVisualIdentity": 7308,
        "HASH32": -771741732,
        "VendorRecipe_AchievementItems": [],
        "Inflection": "",
        "Equip_AchievementItemsKey": 2518,
        "IsCorrupted": false,
        "Identify_AchievementItems": [],
        "IdentifyMagic_AchievementItems": [],
        "FragmentBaseItemTypesKey": null,
        "Unknown24": false,
        "Unknown25": null,
        "Unknown26": null,
        "Unknown27": false,
        "TradeMarketCategory": null,
        "Unmodifiable": false,
        "Achievement": [
            9387
        ],
        "Unknown31": [],
        "IgnoreQuantBonus": false,
        "Unknown33": false
    },
    {
        "_rid": 5668,
        "Id": "Metadata/Items/Weapons/TwoHandWeapons/Staves/StaffE1",
        "ItemClassesKey": 14,
        "Width": 2,
        "Height": 4,
        "Name": "Transformer Staff",
        "InheritsFrom": "Metadata/Items/Weapons/TwoHandWeapons/Staves/AbstractStaff",
        "DropLevel": 30,
        "FlavourTextKey": null,
        "Implicit_ModsKeys": [
            24101
        ],
        "SizeOnGround": 3,
        "SoundEffect": null,
        "TagsKeys": [
            33,
            1061
        ],
        "ModDomain": 1,
        "SiteVisibility": 1,
        "ItemVisualIdentity": 13712,
        "HASH32": 1478624943,
        "VendorRecipe_AchievementItems": [],
        "Inflection": "",
        "Equip_AchievementItemsKey": 7320,
        "IsCorrupted": false,
        "Identify_AchievementItems": [],
        "IdentifyMagic_AchievementItems": [],
        "FragmentBaseItemTypesKey": null,
        "Unknown24": false,
        "Unknown25": null,
        "Unknown26": null,
        "Unknown27": false,
        "TradeMarketCategory": null,
        "Unmodifiable": false,
        "Achievement": [
            10449
        ],
        "Unknown31": [],
        "IgnoreQuantBonus": false,
        "Unknown33": false
    },
    {
        "_rid": 5669,
        "Id": "Metadata/Items/Weapons/TwoHandWeapons/Staves/StaffE2",
        "ItemClassesKey": 14,
        "Width": 2,
        "Height": 4,
        "Name": "Reciprocation Staff",
        "InheritsFrom": "Metadata/Items/Weapons/TwoHandWeapons/Staves/AbstractStaff",
        "DropLevel": 50,
        "FlavourTextKey": null,
        "Implicit_ModsKeys": [
            24102
        ],
        "SizeOnGround": 3,
        "SoundEffect": null,
        "TagsKeys": [
            33,
            1061
        ],
        "ModDomain": 1,
        "SiteVisibility": 1,
        "ItemVisualIdentity": 13712,
        "HASH32": -2123301032,
        "VendorRecipe_AchievementItems": [],
        "Inflection": "",
        "Equip_AchievementItemsKey": 7320,
        "IsCorrupted": false,
        "Identify_AchievementItems": [],
        "IdentifyMagic_AchievementItems": [],
        "FragmentBaseItemTypesKey": null,
        "Unknown24": false,
        "Unknown25": null,
        "Unknown26": null,
        "Unknown27": false,
        "TradeMarketCategory": null,
        "Unmodifiable": false,
        "Achievement": [
            10449
        ],
        "Unknown31": [],
        "IgnoreQuantBonus": false,
        "Unknown33": false
    },
    {
        "_rid": 5670,
        "Id": "Metadata/Items/Weapons/TwoHandWeapons/Staves/StaffE3",
        "ItemClassesKey": 14,
        "Width": 2,
        "Height": 4,
        "Name": "Battery Staff",
        "InheritsFrom": "Metadata/Items/Weapons/TwoHandWeapons/Staves/AbstractStaff",
        "DropLevel": 70,
        "FlavourTextKey": null,
        "Implicit_ModsKeys": [
            24103
        ],
        "SizeOnGround": 3,
        "SoundEffect": null,
        "TagsKeys": [
            33,
            1061
        ],
        "ModDomain": 1,
        "SiteVisibility": 1,
        "ItemVisualIdentity": 13712,
        "HASH32": -1745611296,
        "VendorRecipe_AchievementItems": [],
        "Inflection": "",
        "Equip_AchievementItemsKey": 7320,
        "IsCorrupted": false,
        "Identify_AchievementItems": [],
        "IdentifyMagic_AchievementItems": [],
        "FragmentBaseItemTypesKey": null,
        "Unknown24": false,
        "Unknown25": null,
        "Unknown26": null,
        "Unknown27": false,
        "TradeMarketCategory": null,
        "Unmodifiable": false,
        "Achievement": [
            10449
        ],
        "Unknown31": [],
        "IgnoreQuantBonus": false,
        "Unknown33": false
    },
    {
        "_rid": 5671,
        "Id": "Metadata/Items/Weapons/TwoHandWeapons/Staves/WarstaffE1",
        "ItemClassesKey": 57,
        "Width": 2,
        "Height": 4,
        "Name": "Capacity Rod",
        "InheritsFrom": "Metadata/Items/Weapons/TwoHandWeapons/Staves/AbstractWarstaff",
        "DropLevel": 30,
        "FlavourTextKey": null,
        "Implicit_ModsKeys": [
            24115
        ],
        "SizeOnGround": 3,
        "SoundEffect": null,
        "TagsKeys": [
            33,
            1061
        ],
        "ModDomain": 1,
        "SiteVisibility": 1,
        "ItemVisualIdentity": 13713,
        "HASH32": -1172609946,
        "VendorRecipe_AchievementItems": [],
        "Inflection": "",
        "Equip_AchievementItemsKey": 7320,
        "IsCorrupted": false,
        "Identify_AchievementItems": [],
        "IdentifyMagic_AchievementItems": [],
        "FragmentBaseItemTypesKey": null,
        "Unknown24": false,
        "Unknown25": null,
        "Unknown26": null,
        "Unknown27": false,
        "TradeMarketCategory": null,
        "Unmodifiable": false,
        "Achievement": [
            10449
        ],
        "Unknown31": [],
        "IgnoreQuantBonus": false,
        "Unknown33": false
    },
    {
        "_rid": 5672,
        "Id": "Metadata/Items/Weapons/TwoHandWeapons/Staves/WarstaffE2",
        "ItemClassesKey": 57,
        "Width": 2,
        "Height": 4,
        "Name": "Potentiality Rod",
        "InheritsFrom": "Metadata/Items/Weapons/TwoHandWeapons/Staves/AbstractWarstaff",
        "DropLevel": 50,
        "FlavourTextKey": null,
        "Implicit_ModsKeys": [
            24115
        ],
        "SizeOnGround": 3,
        "SoundEffect": null,
        "TagsKeys": [
            33,
            1061
        ],
        "ModDomain": 1,
        "SiteVisibility": 1,
        "ItemVisualIdentity": 13713,
        "HASH32": -1974431143,
        "VendorRecipe_AchievementItems": [],
        "Inflection": "",
        "Equip_AchievementItemsKey": 7320,
        "IsCorrupted": false,
        "Identify_AchievementItems": [],
        "IdentifyMagic_AchievementItems": [],
        "FragmentBaseItemTypesKey": null,
        "Unknown24": false,
        "Unknown25": null,
        "Unknown26": null,
        "Unknown27": false,
        "TradeMarketCategory": null,
        "Unmodifiable": false,
        "Achievement": [
            10449
        ],
        "Unknown31": [],
        "IgnoreQuantBonus": false,
        "Unknown33": false
    },
    {
        "_rid": 5673,
        "Id": "Metadata/Items/Weapons/TwoHandWeapons/Staves/WarstaffE3",
        "ItemClassesKey": 57,
        "Width": 2,
        "Height": 4,
        "Name": "Eventuality Rod",
        "InheritsFrom": "Metadata/Items/Weapons/TwoHandWeapons/Staves/AbstractWarstaff",
        "DropLevel": 70,
        "FlavourTextKey": null,
        "Implicit_ModsKeys": [
            24115
        ],
        "SizeOnGround": 3,
        "SoundEffect": null,
        "TagsKeys": [
            33,
            1061
        ],
        "ModDomain": 1,
        "SiteVisibility": 1,
        "ItemVisualIdentity": 13713,
        "HASH32": 1334038916,
        "VendorRecipe_AchievementItems": [],
        "Inflection": "",
        "Equip_AchievementItemsKey": 7320,
        "IsCorrupted": false,
        "Identify_AchievementItems": [],
        "IdentifyMagic_AchievementItems": [],
        "FragmentBaseItemTypesKey": null,
        "Unknown24": false,
        "Unknown25": null,
        "Unknown26": null,
        "Unknown27": false,
        "TradeMarketCategory": null,
        "Unmodifiable": false,
        "Achievement": [
            10449
        ],
        "Unknown31": [],
        "IgnoreQuantBonus": false,
        "Unknown33": false
    },
    {
        "_rid": 11634,
        "Id": "Metadata/Items/Weapons/TwoHandWeapons/Staves/WarstaffGamble",
        "ItemClassesKey": 61,
        "Width": 2,
        "Height": 4,
        "Name": "Random Warstaff",
        "InheritsFrom": "Metadata/Items/Item",
        "DropLevel": 13,
        "FlavourTextKey": null,
        "Implicit_ModsKeys": [],
        "SizeOnGround": 3,
        "SoundEffect": null,
        "TagsKeys": [],
        "ModDomain": 1,
        "SiteVisibility": 0,
        "ItemVisualIdentity": 14458,
        "HASH32": 1866299938,
        "VendorRecipe_AchievementItems": [],
        "Inflection": "",
        "Equip_AchievementItemsKey": null,
        "IsCorrupted": false,
        "Identify_AchievementItems": [],
        "IdentifyMagic_AchievementItems": [],
        "FragmentBaseItemTypesKey": null,
        "Unknown24": false,
        "Unknown25": null,
        "Unknown26": null,
        "Unknown27": true,
        "TradeMarketCategory": null,
        "Unmodifiable": false,
        "Achievement": [],
        "Unknown31": [],
        "IgnoreQuantBonus": false,
        "Unknown33": false
    },
    {
        "_rid": 11636,
        "Id": "Metadata/Items/Weapons/TwoHandWeapons/Staves/StaffGamble",
        "ItemClassesKey": 61,
        "Width": 2,
        "Height": 4,
        "Name": "Random Staff",
        "InheritsFrom": "Metadata/Items/Item",
        "DropLevel": 4,
        "FlavourTextKey": null,
        "Implicit_ModsKeys": [],
        "SizeOnGround": 3,
        "SoundEffect": null,
        "TagsKeys": [],
        "ModDomain": 1,
        "SiteVisibility": 0,
        "ItemVisualIdentity": 14460,
        "HASH32": -434009601,
        "VendorRecipe_AchievementItems": [],
        "Inflection": "",
        "Equip_AchievementItemsKey": null,
        "IsCorrupted": false,
        "Identify_AchievementItems": [],
        "IdentifyMagic_AchievementItems": [],
        "FragmentBaseItemTypesKey": null,
        "Unknown24": false,
        "Unknown25": null,
        "Unknown26": null,
        "Unknown27": true,
        "TradeMarketCategory": null,
        "Unmodifiable": false,
        "Achievement": [],
        "Unknown31": [],
        "IgnoreQuantBonus": false,
        "Unknown33": false
    }
]